dpctl/DPCTLSyclInterface.dll
dpctl/DPCTLSyclInterface.lib
dpctl/__init__.pxd
dpctl/__init__.py
dpctl/__main__.py
dpctl/_backend.pxd
dpctl/_device_selection.py
dpctl/_diagnostics.cp310-win_amd64.pyd
dpctl/_init_helper.py
dpctl/_sycl_context.cp310-win_amd64.pyd
dpctl/_sycl_context.pxd
dpctl/_sycl_device.cp310-win_amd64.pyd
dpctl/_sycl_device.pxd
dpctl/_sycl_device_factory.cp310-win_amd64.pyd
dpctl/_sycl_device_factory.pxd
dpctl/_sycl_event.cp310-win_amd64.pyd
dpctl/_sycl_event.pxd
dpctl/_sycl_platform.cp310-win_amd64.pyd
dpctl/_sycl_platform.pxd
dpctl/_sycl_queue.cp310-win_amd64.pyd
dpctl/_sycl_queue.pxd
dpctl/_sycl_queue_manager.cp310-win_amd64.pyd
dpctl/_sycl_queue_manager.pxd
dpctl/_sycl_timer.py
dpctl/_version.py
dpctl/enum_types.py
dpctl/sycl.pxd
dpctl/include/dpctl4pybind11.hpp
dpctl/include/dpctl_capi.h
dpctl/include/dpctl_sycl_interface.h
dpctl/include/dpctl/_sycl_context.h
dpctl/include/dpctl/_sycl_context_api.h
dpctl/include/dpctl/_sycl_device.h
dpctl/include/dpctl/_sycl_device_api.h
dpctl/include/dpctl/_sycl_event.h
dpctl/include/dpctl/_sycl_event_api.h
dpctl/include/dpctl/_sycl_queue.h
dpctl/include/dpctl/_sycl_queue_api.h
dpctl/include/dpctl/memory/_memory.h
dpctl/include/dpctl/memory/_memory_api.h
dpctl/include/dpctl/program/_program.h
dpctl/include/dpctl/program/_program_api.h
dpctl/include/dpctl/tensor/_usmarray.h
dpctl/include/dpctl/tensor/_usmarray_api.h
dpctl/include/syclinterface/dpctl_data_types.h
dpctl/include/syclinterface/dpctl_device_selection.hpp
dpctl/include/syclinterface/dpctl_error_handler_type.h
dpctl/include/syclinterface/dpctl_service.h
dpctl/include/syclinterface/dpctl_sycl_context_interface.h
dpctl/include/syclinterface/dpctl_sycl_device_interface.h
dpctl/include/syclinterface/dpctl_sycl_device_manager.h
dpctl/include/syclinterface/dpctl_sycl_device_selector_interface.h
dpctl/include/syclinterface/dpctl_sycl_enum_types.h
dpctl/include/syclinterface/dpctl_sycl_event_interface.h
dpctl-0.21.1.dist-info/licenses/LICENSE
dpctl-0.21.1.dist-info/METADATA
dpctl-0.21.1.dist-info/WHEEL
dpctl-0.21.1.dist-info/top_level.txt
dpctl-0.21.1.dist-info/RECORD
