Metadata-Version: 2.4
Name: dpctl
Version: 0.21.1
Summary: A lightweight Python wrapper for a subset of SYCL.
Home-page: https://github.com/IntelPython/dpctl
Author: Intel Corporation
License: Apache 2.0
Project-URL: Changelog, https://github.com/IntelPython/dpctl/blob/master/CHANGELOG.md
Project-URL: Documentation, https://intelpython.github.io/dpctl/
Project-URL: Homepage, https://github.com/IntelPython/dpctl
Project-URL: Issues, https://github.com/IntelPython/dpctl/issues
Project-URL: Repository, https://github.com/IntelPython/dpctl.git
Keywords: dpctl,intel,oneapi,dpcpp
Classifier: Development Status :: 4 - Beta
Classifier: Intended Audience :: Science/Research
Classifier: Intended Audience :: Developers
Classifier: License :: OSI Approved :: Apache Software License
Classifier: Programming Language :: C
Classifier: Programming Language :: Python
Classifier: Programming Language :: Python :: 3
Classifier: Programming Language :: Python :: 3.9
Classifier: Programming Language :: Python :: 3.10
Classifier: Programming Language :: Python :: 3.11
Classifier: Programming Language :: Python :: 3.12
Classifier: Programming Language :: Python :: 3.13
Classifier: Programming Language :: Python :: 3.14
Classifier: Programming Language :: Python :: Implementation :: CPython
Classifier: Topic :: Software Development
Classifier: Topic :: Scientific/Engineering
Classifier: Operating System :: Microsoft :: Windows
Classifier: Operating System :: POSIX :: Linux
Classifier: Operating System :: POSIX
Classifier: Operating System :: Unix
Requires-Python: >=3.9
License-File: LICENSE
Provides-Extra: coverage
Provides-Extra: docs
Dynamic: home-page
Dynamic: license-file
Requires-Dist: intel-cmplr-lib-rt >=2025.3,<2026.0a0
Requires-Dist: intel-sycl-rt >=2025.3,<2026.0a0
Requires-Dist: numpy
